README.txt
setup.cfg
setup.py
Cryptotranslator.egg-info/PKG-INFO
Cryptotranslator.egg-info/SOURCES.txt
Cryptotranslator.egg-info/dependency_links.txt
Cryptotranslator.egg-info/requires.txt
Cryptotranslator.egg-info/top_level.txt
cryptotranslator/__init__.py
cryptotranslator.egg-info/PKG-INFO
cryptotranslator.egg-info/SOURCES.txt
cryptotranslator.egg-info/dependency_links.txt
cryptotranslator.egg-info/requires.txt
cryptotranslator.egg-info/top_level.txt