Metadata-Version: 1.1
Name: cryptotranslator
Version: 0.1.1
Summary: Names translation for cryptocurrency pairs and tickets.
Home-page: https://github.com/estebance/crypto_translator
Author: Esteban Ceron
Author-email: restebance@gmail.com
License: UNKNOWN
Keywords: standard
Platform: UNKNOWN
Classifier: Development Status :: 3 - Alpha
Classifier: Programming Language :: Python :: 3
Classifier: Programming Language :: Python :: 3.4
Classifier: Programming Language :: Python :: 3.5
Classifier: Programming Language :: Python :: 3.6
